{
  "id": 18,
  "title": "Campeonato Lisboa e Alto Alentejo Jovem",
  "subtitle": "Infantis Masculinos",
  "swimDistance": "",
  "swimLaps": "",
  "cynclingDistance": "",
  "cyclingLaps": "",
  "runDistance": "",
  "runLaps": "",
  "actualDate": "2022-02-26",
  "actualTime": "",
  "airTemperature": "",
  "waterTemperature": "",
  "wetSuit": "",
  "raceReference": "20220226LAA001-004",
  "results": [
    {
      "rank": "1",
      "licence": "107079",
      "raceNumber": "761",
      "name": "Dinis Cabral",
      "ageGroup": "INF",
      "team": "Escola Tri-Azeitonense",
      "total": "00:11:22",
      "gap": "00:00:00",
      "points": "150"
    },
    {
      "rank": "2",
      "licence": "104696",
      "raceNumber": "977",
      "name": "André Martins",
      "ageGroup": "INF",
      "team": "Sport Lisboa e Benfica",
      "total": "00:11:54",
      "gap": "00:00:32",
      "points": "140"
    },
    {
      "rank": "3",
      "licence": "104689",
      "raceNumber": "1044",
      "name": "Santiago Santos",
      "ageGroup": "INF",
      "team": "Sport Lisboa e Benfica",
      "total": "00:11:56",
      "gap": "00:00:34",
      "points": "130"
    },
    {
      "rank": "4",
      "licence": "107301",
      "raceNumber": "1204",
      "name": "Gonçalo José",
      "ageGroup": "INF",
      "team": "Palmela Desporto / Tripla Rotação",
      "total": "00:12:12",
      "gap": "00:00:50",
      "points": "125"
    },
    {
      "rank": "5",
      "licence": "105848",
      "raceNumber": "1080",
      "name": "Bernardo Miranda",
      "ageGroup": "INF",
      "team": "Sport Lisboa e Benfica",
      "total": "00:12:18",
      "gap": "00:00:56",
      "points": "120"
    },
    {
      "rank": "6",
      "licence": "106119",
      "raceNumber": "1231",
      "name": "Ivan Fragoso",
      "ageGroup": "INF",
      "team": "AmoraSub/Associação Naval Amorense",
      "total": "00:12:21",
      "gap": "00:00:59",
      "points": "115"
    },
    {
      "rank": "7",
      "licence": "107847",
      "raceNumber": "492",
      "name": "Leonardo Cardoso",
      "ageGroup": "INF",
      "team": "Palmela Desporto / Tripla Rotação",
      "total": "00:12:57",
      "gap": "00:01:35",
      "points": "110"
    },
    {
      "rank": "8",
      "licence": "106733",
      "raceNumber": "252",
      "name": "Miguel Neto",
      "ageGroup": "INF",
      "team": "Aminata Triatlo",
      "total": "00:12:59",
      "gap": "00:01:37",
      "points": "108"
    },
    {
      "rank": "9",
      "licence": "108281",
      "raceNumber": "1056",
      "name": "Gil Campos",
      "ageGroup": "INF",
      "team": "Escola Triatlo Santo António Évora",
      "total": "00:13:02",
      "gap": "00:01:40",
      "points": "106"
    },
    {
      "rank": "10",
      "licence": "107227",
      "raceNumber": "1013",
      "name": "Gui Alves",
      "ageGroup": "INF",
      "team": "Alhandra Sporting Club",
      "total": "00:13:10",
      "gap": "00:01:48",
      "points": "104"
    },
    {
      "rank": "11",
      "licence": "108252",
      "raceNumber": "974",
      "name": "João Potes",
      "ageGroup": "INF",
      "team": "Escola Triatlo Santo António Évora",
      "total": "00:13:15",
      "gap": "00:01:53",
      "points": "102"
    },
    {
      "rank": "12",
      "licence": "107739",
      "raceNumber": "402",
      "name": "Petri Tavares",
      "ageGroup": "INF",
      "team": "Palmela Desporto / Tripla Rotação",
      "total": "00:13:15",
      "gap": "00:01:53",
      "points": "100"
    },
    {
      "rank": "13",
      "licence": "107107",
      "raceNumber": "819",
      "name": "Diogo Marcão Santos",
      "ageGroup": "INF",
      "team": "Alhandra Sporting Club",
      "total": "00:13:48",
      "gap": "00:02:26",
      "points": "98"
    },
    {
      "rank": "14",
      "licence": "107245",
      "raceNumber": "1143",
      "name": "Eduardo Couto Lopes",
      "ageGroup": "INF",
      "team": "AmoraSub/Associação Naval Amorense",
      "total": "00:13:53",
      "gap": "00:02:31",
      "points": "96"
    },
    {
      "rank": "15",
      "licence": "EXTRA",
      "raceNumber": "1130",
      "name": "Henrique Miranda",
      "ageGroup": "INF",
      "team": "X Não Federado",
      "total": "00:14:08",
      "gap": "00:02:46",
      "points": ""
    },
    {
      "rank": "16",
      "licence": "107464",
      "raceNumber": "94",
      "name": "Tomás Moreira",
      "ageGroup": "INF",
      "team": "Escola Triatlo Santo António Évora",
      "total": "00:14:44",
      "gap": "00:03:22",
      "points": "94"
    },
    {
      "rank": "17",
      "licence": "106837",
      "raceNumber": "423",
      "name": "Arnaldo Camões",
      "ageGroup": "INF",
      "team": "Palmela Desporto / Tripla Rotação",
      "total": "00:14:52",
      "gap": "00:03:30",
      "points": "92"
    },
    {
      "rank": "18",
      "licence": "105009",
      "raceNumber": "348",
      "name": "David Pacheco",
      "ageGroup": "INF",
      "team": "SFRAA TRIATLO",
      "total": "00:14:58",
      "gap": "00:03:36",
      "points": "90"
    },
    {
      "rank": "19",
      "licence": "108243",
      "raceNumber": "968",
      "name": "Tomás Carrageta",
      "ageGroup": "INF",
      "team": "Escola Triatlo Santo António Évora",
      "total": "00:15:04",
      "gap": "00:03:42",
      "points": "88"
    },
    {
      "rank": "20",
      "licence": "107912",
      "raceNumber": "658",
      "name": "Afonso Calha",
      "ageGroup": "INF",
      "team": "Outsystems Olímpico de Oeiras",
      "total": "00:15:18",
      "gap": "00:03:56",
      "points": "86"
    },
    {
      "rank": "21",
      "licence": "EXTRA",
      "raceNumber": "725",
      "name": "Yanni Flohr",
      "ageGroup": "INF",
      "team": "Individual",
      "total": "00:15:22",
      "gap": "00:04:00",
      "points": ""
    },
    {
      "rank": "22",
      "licence": "108029",
      "raceNumber": "772",
      "name": "Carlos Guerreiro",
      "ageGroup": "INF",
      "team": "TRIATLO - Santo André Sport Club",
      "total": "00:15:35",
      "gap": "00:04:13",
      "points": "84"
    },
    {
      "rank": "23",
      "licence": "106099",
      "raceNumber": "1224",
      "name": "Rafael Gutsulyak Romão Pinela",
      "ageGroup": "INF",
      "team": "AMICICLO GRÂNDOLA",
      "total": "00:15:35",
      "gap": "00:04:13",
      "points": "82"
    },
    {
      "rank": "24",
      "licence": "105417",
      "raceNumber": "456",
      "name": "Diogo Pardal",
      "ageGroup": "INF",
      "team": "Clube de Natação da Amadora",
      "total": "00:15:56",
      "gap": "00:04:34",
      "points": "80"
    },
    {
      "rank": "25",
      "licence": "107899",
      "raceNumber": "644",
      "name": "Salvador Varela",
      "ageGroup": "INF",
      "team": "Alhandra Sporting Club",
      "total": "00:16:03",
      "gap": "00:04:41",
      "points": "78"
    },
    {
      "rank": "26",
      "licence": "EXTRA",
      "raceNumber": "8086",
      "name": "Rodrigo Santiago",
      "ageGroup": "INF",
      "team": "X Não Federado",
      "total": "00:16:13",
      "gap": "00:04:51",
      "points": ""
    },
    {
      "rank": "27",
      "licence": "106685",
      "raceNumber": "168",
      "name": "Tomás Ribeiro",
      "ageGroup": "INF",
      "team": "SFRAA TRIATLO",
      "total": "00:16:25",
      "gap": "00:05:03",
      "points": "77"
    },
    {
      "rank": "28",
      "licence": "106532",
      "raceNumber": "1430",
      "name": "Martim Rodrigues Grilo",
      "ageGroup": "INF",
      "team": "CNCVG",
      "total": "00:16:42",
      "gap": "00:05:20",
      "points": "76"
    },
    {
      "rank": "29",
      "licence": "108286",
      "raceNumber": "1063",
      "name": "António Sales",
      "ageGroup": "INF",
      "team": "Escola Triatlo Santo António Évora",
      "total": "00:18:31",
      "gap": "00:07:09",
      "points": "75"
    },
    {
      "rank": "30",
      "licence": "108026",
      "raceNumber": "765",
      "name": "Tiago Sousa",
      "ageGroup": "INF",
      "team": "TRIATLO - Santo André Sport Club",
      "total": "00:18:58",
      "gap": "00:07:36",
      "points": "74"
    },
    {
      "rank": "31",
      "licence": "EXTRA",
      "raceNumber": "872",
      "name": "Benjamin Lachman",
      "ageGroup": "INF",
      "team": "Individual",
      "total": "00:21:35",
      "gap": "00:10:13",
      "points": ""
    }
  ]
}
